AUTHOR.txt
CHANGES.txt
COPYRIGHT.txt
LICENSE.txt
README.txt
bootstrap.py
buildout.cfg
setup.py
src/z3c/__init__.py
src/z3c.recipe.runscript.egg-info/PKG-INFO
src/z3c.recipe.runscript.egg-info/SOURCES.txt
src/z3c.recipe.runscript.egg-info/dependency_links.txt
src/z3c.recipe.runscript.egg-info/entry_points.txt
src/z3c.recipe.runscript.egg-info/namespace_packages.txt
src/z3c.recipe.runscript.egg-info/not-zip-safe
src/z3c.recipe.runscript.egg-info/requires.txt
src/z3c.recipe.runscript.egg-info/top_level.txt
src/z3c/recipe/__init__.py
src/z3c/recipe/runscript/README.txt
src/z3c/recipe/runscript/__init__.py
src/z3c/recipe/runscript/tests/__init__.py
src/z3c/recipe/runscript/tests/fooscripts.py
src/z3c/recipe/runscript/tests/test_doc.py